UIAutomationFramework/__init__.py
UIAutomationFramework/apps/__init__.py
UIAutomationFramework/common/UiAutoDriver.py
UIAutomationFramework/common/UiServer.py
UIAutomationFramework/common/__init__.py
UIAutomationFramework/common/apiElement.py
UIAutomationFramework/test/__init__.py
UIAutomationFramework/test/android_examples.py
UIAutomationFramework/test/ios_exmples.py
UI_Automation_Framework-0.1.6.1.dist-info/METADATA
UI_Automation_Framework-0.1.6.1.dist-info/WHEEL
UI_Automation_Framework-0.1.6.1.dist-info/top_level.txt
UI_Automation_Framework-0.1.6.1.dist-info/RECORD
