Metadata-Version: 2.1
Name: UI-Automation-Framework
Version: 0.1.6.1
Summary: UI自动化框架，集成APPIUM、selenium
Home-page: https://github.com/chenzheng102/UI-Automation-Framework
Author: lzh
Author-email: 743872668@qq.com
License: UNKNOWN
Platform: UNKNOWN
Classifier: Programming Language :: Python :: 3
Classifier: License :: OSI Approved :: MIT License
Classifier: Operating System :: OS Independent
